dot2dict/__init__.py
dot2dict/docs.py
dot2dict/dot2dict_typer.py
dot2dict/example.md
dot2dict-0.4.1.dist-info/entry_points.txt
dot2dict-0.4.1.dist-info/WHEEL
dot2dict-0.4.1.dist-info/METADATA
dot2dict-0.4.1.dist-info/RECORD
