Metadata-Version: 2.1
Name: dot2dict
Version: 0.4.1
Summary: JSON dot notation to Python Dictionary 🐍 / Ruby Hash ♦️ Notation Converter
Home-page: https://pypi.org/project/dot2dict/
Keywords: cli,json,dot_notation,converter,dot to dictionary,dot to hash,Python Dictionary,Ruby Hash
Author: Sumanth
Author-email: sumanthreddystar@gmail.com
Maintainer: Sumanth
Maintainer-email: sumanthreddystar@gmail.com
Requires-Python: >=3.6,<4.0
Classifier: Programming Language :: Python :: 3
Classifier: Programming Language :: Python :: 3.10
Classifier: Programming Language :: Python :: 3.6
Classifier: Programming Language :: Python :: 3.7
Classifier: Programming Language :: Python :: 3.8
Classifier: Programming Language :: Python :: 3.9
Requires-Dist: rich (>=12.5.1,<13.0.0)
Requires-Dist: typer[all] (>=0.6.1,<0.7.0)
Project-URL: Bug Tracker, https://github.com/python-poetry/poetry/issues
Project-URL: Documentation, https://github.com/insumanth/dot2dict/blob/main/README.md
Project-URL: Repository, https://github.com/insumanth/dot2dict
